jaraco/logging.py
jaraco.logging-3.3.0.dist-info/LICENSE
jaraco.logging-3.3.0.dist-info/METADATA
jaraco.logging-3.3.0.dist-info/WHEEL
jaraco.logging-3.3.0.dist-info/top_level.txt
jaraco.logging-3.3.0.dist-info/RECORD
